ipyleaflet/__init__.py
ipyleaflet/_version.py
ipyleaflet/basemaps.py
ipyleaflet/leaflet.py
ipyleaflet/projections.py
ipyleaflet/velocity.py
ipyleaflet/xarray_ds.py
ipyleaflet/external/__init__.py
ipyleaflet/external/here.py
ipyleaflet/labextension/package.json
ipyleaflet/labextension/static/056dcd0b0dea7c78019243311551d64b.png
ipyleaflet/labextension/static/07f16cd155661436fe27959eab15c820.png
ipyleaflet/labextension/static/0b50583aa1b8ff230b57b92263e47a3e.png
ipyleaflet/labextension/static/0f2c10250081cf1bd9a4d2250b80dba6.png
ipyleaflet/labextension/static/138.dfa150876ef9209879ba.js
ipyleaflet/labextension/static/2273e3d8ad9264b7daa5bdbf8e6b47f8.png
ipyleaflet/labextension/static/243.45f065b556905df86ca2.js
ipyleaflet/labextension/static/243.45f065b556905df86ca2.js.LICENSE.txt
ipyleaflet/labextension/static/292.4107fc80f490ac63e379.js
ipyleaflet/labextension/static/35.eb4b6d6bf1ffeee78ab0.js
ipyleaflet/labextension/static/35ae4b5f1bf198c6d955618b85710d05.png
ipyleaflet/labextension/static/366.4812dc6882dd3f72dc86.js
ipyleaflet/labextension/static/401d815dc206b8dc1b17cd0e37695975.png
ipyleaflet/labextension/static/408.2d9f0740a6db65f5d011.js
ipyleaflet/labextension/static/44a526eed258222515aa21eaffd14a96.png
ipyleaflet/labextension/static/473ee081160a469c95199d70e78f55fa.png
ipyleaflet/labextension/static/4f0283c6ce28e888000e978e537a6a56.png
ipyleaflet/labextension/static/549b33bab7247b619c0292995f5a906b.png
ipyleaflet/labextension/static/550.d5d4cff7dfc1cd2c5db9.js
ipyleaflet/labextension/static/592b7360116d244f9dd932b0c0041982.png
ipyleaflet/labextension/static/665.b94d26724f288e3351eb.js
ipyleaflet/labextension/static/687.6c0a27b7c659dcc31c14.js
ipyleaflet/labextension/static/69fbc9c24b3665b801445c9bccc7017d.png
ipyleaflet/labextension/static/6a1e950d14904d4b6fb5c9bdc3dfad06.png
ipyleaflet/labextension/static/6e8e462555c4b10dbfbc206e8276e6e2.png
ipyleaflet/labextension/static/732.755ed92c4bd1cc1f291b.js
ipyleaflet/labextension/static/738.3cb98a41cc77eed3dc2d.js
ipyleaflet_pmtiles-0.17.4.dist-info/LICENSE
ipyleaflet_pmtiles-0.17.4.dist-info/METADATA
ipyleaflet_pmtiles-0.17.4.dist-info/WHEEL
ipyleaflet_pmtiles-0.17.4.dist-info/top_level.txt
ipyleaflet_pmtiles-0.17.4.dist-info/RECORD
